<?xml version="1.0" encoding="UTF-8"?><record_update>
    <sys_choice action="DELETE" field="u_what_needed" table="x_58872_needit_needit" version="3">
        <sys_choice_set action="DELETE">
            <element>u_what_needed</element>
            <name>x_58872_needit_needit</name>
            <sys_class_name/>
            <sys_created_by/>
            <sys_created_on/>
            <sys_id/>
            <sys_mod_count/>
            <sys_name/>
            <sys_package/>
            <sys_policy/>
            <sys_scope/>
            <sys_update_name/>
            <sys_updated_by/>
            <sys_updated_on>2020-05-04 13:24:43</sys_updated_on>
        </sys_choice_set>
    </sys_choice>
    <sys_update_version action="INSERT_OR_UPDATE">
        <action>DELETE</action>
        <application/>
        <file_path/>
        <instance_id>4acca33ddb321b400e785d00cf961971</instance_id>
        <instance_name>dev61952</instance_name>
        <name>sys_choice_x_58872_needit_needit_u_what_needed</name>
        <payload><![CDATA[<?xml version="1.0" encoding="UTF-8"?><record_update><sys_choice action="DELETE" field="u_what_needed" table="x_58872_needit_needit" version="3"><sys_choice_set action="DELETE"><element>u_what_needed</element><name>x_58872_needit_needit</name><sys_class_name/><sys_created_by/><sys_created_on/><sys_id/><sys_mod_count/><sys_name/><sys_package/><sys_policy/><sys_scope/><sys_update_name/><sys_updated_by/><sys_updated_on>2020-05-04 13:24:43</sys_updated_on></sys_choice_set></sys_choice></record_update>]]></payload>
        <payload_hash>-429457270</payload_hash>
        <record_name>x_58872_needit_needit.u_what_needed</record_name>
        <reverted_from/>
        <source>2d6c6ff5db20101063ab1780399619f9</source>
        <source_table>sys_update_set</source_table>
        <state>previous</state>
        <sys_created_by>admin</sys_created_by>
        <sys_created_on>2020-05-04 13:24:43</sys_created_on>
        <sys_id>302fbccadbe0101063ab1780399619d3</sys_id>
        <sys_mod_count>0</sys_mod_count>
        <sys_recorded_at>171dfdc35900000001</sys_recorded_at>
        <sys_updated_by>admin</sys_updated_by>
        <sys_updated_on>2020-05-04 13:24:43</sys_updated_on>
        <type>Choice list</type>
        <update_guid>b82fbcca48e010106994e90e59bb0ad2</update_guid>
        <update_guid_history>b82fbcca48e010106994e90e59bb0ad2:-429457270,742fbccacde010103c23db742f8c07cf:-1645599408,f02fbccad1e010106279b0b3687fd5cc:872629236,702fbccab0e01010c63339ecaf6611c9:-1368518222,fc2fbcca23e010103b3e2f489dbaa3c5:-835683595,7c2fbccab3e01010f097bd0e14b8c0c2:1301214599,f82fbccab3e0101080f5596433acebbf:-217878606,782fbccad5e01010711197d2ad3bb0bc:391391694,078be8ce1ba01010d4878107b7e1cb40:282754765</update_guid_history>
    </sys_update_version>
    <sys_metadata_delete action="INSERT_OR_UPDATE">
        <sys_audit_delete/>
        <sys_class_name>sys_metadata_delete</sys_class_name>
        <sys_created_by>admin</sys_created_by>
        <sys_created_on>2020-05-04 13:24:51</sys_created_on>
        <sys_db_object display_value="" name="sys_choice_set">sys_choice_set</sys_db_object>
        <sys_id>222f300edbe0101063ab17803996196d</sys_id>
        <sys_metadata>222f300edbe0101063ab17803996196d</sys_metadata>
        <sys_mod_count>0</sys_mod_count>
        <sys_name>u_what_needed</sys_name>
        <sys_package display_value="NeedIt" source="x_58872_needit">6ead8e780f603200cd674f8ce1050ed1</sys_package>
        <sys_parent/>
        <sys_policy/>
        <sys_scope display_value="NeedIt">6ead8e780f603200cd674f8ce1050ed1</sys_scope>
        <sys_scope_delete display_value="">94872a8897db403e8ee69a431de2fca4</sys_scope_delete>
        <sys_update_name>sys_choice_x_58872_needit_needit_u_what_needed</sys_update_name>
        <sys_update_version display_value="sys_choice_x_58872_needit_needit_u_what_needed">302fbccadbe0101063ab1780399619d3</sys_update_version>
        <sys_updated_by>admin</sys_updated_by>
        <sys_updated_on>2020-05-04 13:24:51</sys_updated_on>
    </sys_metadata_delete>
</record_update>
